foundationlive/__init__.py
foundationlive/common.py
foundationlive/config.py
foundationlive/googlesheets.py
foundationlive/lib.py
foundationlive/main.py
foundationlive/menu.py
foundationlive/model.py
foundationlive/writer.py
foundationlive/templates/view_csv.j2
foundationlive/templates/view_hours_worked_per_day.j2
foundationlive/templates/view_hours_worked_per_day_summary.j2
foundationlive/templates/view_hours_worked_per_task.j2
foundationlive/templates/view_invoices.j2
foundationlive-0.0.63.dist-info/LICENSE.txt
foundationlive-0.0.63.dist-info/METADATA
foundationlive-0.0.63.dist-info/WHEEL
foundationlive-0.0.63.dist-info/entry_points.txt
foundationlive-0.0.63.dist-info/top_level.txt
foundationlive-0.0.63.dist-info/RECORD
