Metadata-Version: 2.1
Name: foundationlive
Version: 0.0.63
Summary: Add a short description here!
Home-page: https://github.com/pyscaffold/pyscaffold/
Author: Taylor Monacelli
Author-email: taylormonacelli@gmail.com
License: MIT
Project-URL: Documentation, https://pyscaffold.org/
Platform: any
Classifier: Development Status :: 4 - Beta
Classifier: Programming Language :: Python
License-File: LICENSE.txt
Requires-Dist: pydantic
Requires-Dist: durations
Requires-Dist: jinja2
Requires-Dist: humanize
Requires-Dist: python-dateutil
Requires-Dist: pyyaml
Requires-Dist: pytz
Requires-Dist: timeago
Requires-Dist: gspread
Requires-Dist: oauth2client
Requires-Dist: inflect
Requires-Dist: holidays
Requires-Dist: platformdirs
Requires-Dist: python-dotenv
Requires-Dist: simple-term-menu
Requires-Dist: importlib-metadata ; python_version < "3.8"
Provides-Extra: testing
Requires-Dist: setuptools ; extra == 'testing'
Requires-Dist: pytest ; extra == 'testing'
Requires-Dist: pytest-cov ; extra == 'testing'
